libopensonic/__init__.py
libopensonic/_version.py
libopensonic/async_connection.py
libopensonic/conn_base.py
libopensonic/connection.py
libopensonic/errors.py
libopensonic/media/__init__.py
libopensonic/media/media_types.py
py_opensonic-8.1.1.dist-info/licenses/LICENSE
py_opensonic-8.1.1.dist-info/METADATA
py_opensonic-8.1.1.dist-info/WHEEL
py_opensonic-8.1.1.dist-info/top_level.txt
py_opensonic-8.1.1.dist-info/RECORD
