Metadata-Version: 2.4
Name: py-opensonic
Version: 8.1.1
Summary: A python wrapper library for the Open Subsonic REST API.  https://opensubsonic.netlify.app/
Home-page: https://github.com/khers/py-opensonic
Author: Eric B. Munson
Author-email: eric@munsonfam.org
Classifier: Development Status :: 5 - Production/Stable
Classifier: Intended Audience :: Developers
Classifier: Intended Audience :: System Administrators
Classifier: Intended Audience :: Information Technology
Classifier: License :: OSI Approved :: GNU General Public License (GPL)
Classifier: Natural Language :: English
Classifier: Operating System :: POSIX
Classifier: Programming Language :: Python
Classifier: Topic :: System :: Systems Administration
Classifier: Topic :: Internet :: WWW/HTTP
Classifier: Topic :: Software Development :: Libraries :: Python Modules
Classifier: Topic :: Software Development :: Libraries
Classifier: Topic :: System
Requires-Python: >=3
License-File: LICENSE
Requires-Dist: aiohttp>=3.13.2
Requires-Dist: requests>=2.31.0
Requires-Dist: mashumaro>=3.15
Dynamic: author
Dynamic: author-email
Dynamic: classifier
Dynamic: description
Dynamic: description-content-type
Dynamic: home-page
Dynamic: license-file
Dynamic: requires-dist
Dynamic: requires-python
Dynamic: summary
